{"id":108,"type":"Normal","category":"Status","power":null,"accuracy":100,"pp":20,"name":{"ja":"えんまく","en":"Smokescreen","zh":"煙幕"},"learnedBy":{"levelUp":[{"pid":4,"type":["Fire"],"name":{"zh":"小火龍","ja":"ヒトカゲ","en":"Charmander"},"level":19},{"pid":5,"type":["Fire"],"name":{"zh":"火恐龍","ja":"リザード","en":"Charmeleon"},"level":20},{"pid":6,"type":["Fire","Flying"],"name":{"zh":"噴火龍","ja":"リザードン","en":"Charizard"},"level":20},{"pid":109,"type":["Poison"],"name":{"zh":"瓦斯彈","ja":"ドガース","en":"Koffing"},"level":25},{"pid":110,"type":["Poison"],"name":{"zh":"雙彈瓦斯","ja":"マタドガス","en":"Weezing"},"level":25},{"pid":116,"type":["Water"],"name":{"zh":"墨海馬","ja":"タッツー","en":"Horsea"},"level":8},{"pid":117,"type":["Water"],"name":{"zh":"海刺龍","ja":"シードラ","en":"Seadra"},"level":1},{"pid":126,"type":["Fire"],"name":{"zh":"鴨嘴火獸","ja":"ブーバー","en":"Magmar"},"level":25},{"pid":155,"type":["Fire"],"name":{"zh":"火球鼠","ja":"ヒノアラシ","en":"Cyndaquil"},"level":6},{"pid":156,"type":["Fire"],"name":{"zh":"火岩鼠","ja":"マグマラシ","en":"Quilava"},"level":1},{"pid":157,"type":["Fire"],"name":{"zh":"火爆獸","ja":"バクフーン","en":"Typhlosion"},"level":1},{"pid":230,"type":["Water","Dragon"],"name":{"zh":"刺龍王","ja":"キングドラ","en":"Kingdra"},"level":1},{"pid":240,"type":["Fire"],"name":{"zh":"鴨嘴寶寶","ja":"ブビィ","en":"Magby"},"level":25},{"pid":324,"type":["Fire"],"name":{"zh":"煤炭龜","ja":"コータス","en":"Torkoal"},"level":14}],"machine":[],"egg":[],"tutor":[]}}