{"id":135,"type":"Normal","category":"Status","power":null,"accuracy":null,"pp":5,"name":{"ja":"タマゴうみ","en":"Soft-Boiled","zh":"生蛋"},"learnedBy":{"levelUp":[{"pid":113,"type":["Normal"],"name":{"zh":"吉利蛋","ja":"ラッキー","en":"Chansey"},"level":13},{"pid":242,"type":["Normal"],"name":{"zh":"幸福蛋","ja":"ハピナス","en":"Blissey"},"level":10}],"machine":[],"egg":[],"tutor":[{"pid":35,"type":["Normal"],"name":{"zh":"皮皮","ja":"ピッピ","en":"Clefairy"}},{"pid":36,"type":["Normal"],"name":{"zh":"皮可西","ja":"ピクシー","en":"Clefable"}},{"pid":151,"type":["Psychic"],"name":{"zh":"夢幻","ja":"ミュウ","en":"Mew"}},{"pid":173,"type":["Normal"],"name":{"zh":"皮寶寶","ja":"ピィ","en":"Cleffa"}},{"pid":175,"type":["Normal"],"name":{"zh":"波克比","ja":"トゲピー","en":"Togepi"}},{"pid":176,"type":["Normal","Flying"],"name":{"zh":"波克基古","ja":"トゲチック","en":"Togetic"}}]}}