{"id":152,"type":"Water","category":"Special","power":100,"accuracy":90,"pp":10,"name":{"ja":"クラブハンマー","en":"Crabhammer","zh":"蟹鉗錘"},"learnedBy":{"levelUp":[{"pid":98,"type":["Water"],"name":{"zh":"大鉗蟹","ja":"クラブ","en":"Krabby"},"level":45},{"pid":99,"type":["Water"],"name":{"zh":"巨鉗蟹","ja":"キングラー","en":"Kingler"},"level":57},{"pid":341,"type":["Water"],"name":{"zh":"龍蝦小兵","ja":"ヘイガニ","en":"Corphish"},"level":34},{"pid":342,"type":["Water","Dark"],"name":{"zh":"鐵螯龍蝦","ja":"シザリガー","en":"Crawdaunt"},"level":38}],"machine":[],"egg":[],"tutor":[]}}