{"id":153,"type":"Normal","category":"Physical","power":250,"accuracy":100,"pp":5,"name":{"ja":"だいばくはつ","en":"Explosion","zh":"大爆炸"},"learnedBy":{"levelUp":[{"pid":74,"type":["Rock","Ground"],"name":{"zh":"小拳石","ja":"イシツブテ","en":"Geodude"},"level":41},{"pid":75,"type":["Rock","Ground"],"name":{"zh":"隆隆石","ja":"ゴローン","en":"Graveler"},"level":53},{"pid":76,"type":["Rock","Ground"],"name":{"zh":"隆隆岩","ja":"ゴローニャ","en":"Golem"},"level":53},{"pid":100,"type":["Electric"],"name":{"zh":"霹靂電球","ja":"ビリリダマ","en":"Voltorb"},"level":46},{"pid":101,"type":["Electric"],"name":{"zh":"頑皮雷彈","ja":"マルマイン","en":"Electrode"},"level":54},{"pid":109,"type":["Poison"],"name":{"zh":"瓦斯彈","ja":"ドガース","en":"Koffing"},"level":41},{"pid":110,"type":["Poison"],"name":{"zh":"雙彈瓦斯","ja":"マタドガス","en":"Weezing"},"level":44},{"pid":204,"type":["Bug"],"name":{"zh":"榛果球","ja":"クヌギダマ","en":"Pineco"},"level":36},{"pid":205,"type":["Bug","Steel"],"name":{"zh":"佛烈托斯","ja":"フォレトス","en":"Forretress"},"level":39},{"pid":273,"type":["Grass"],"name":{"zh":"橡實果","ja":"タネボー","en":"Seedot"},"level":43},{"pid":337,"type":["Rock","Psychic"],"name":{"zh":"月石","ja":"ルナトーン","en":"Lunatone"},"level":49},{"pid":338,"type":["Rock","Psychic"],"name":{"zh":"太陽岩","ja":"ソルロック","en":"Solrock"},"level":49},{"pid":343,"type":["Ground","Psychic"],"name":{"zh":"天秤偶","ja":"ヤジロン","en":"Baltoy"},"level":45},{"pid":344,"type":["Ground","Psychic"],"name":{"zh":"念力土偶","ja":"ネンドール","en":"Claydol"},"level":55},{"pid":377,"type":["Rock"],"name":{"zh":"雷吉洛克","ja":"レジロック","en":"Regirock"},"level":1},{"pid":378,"type":["Ice"],"name":{"zh":"雷吉艾斯","ja":"レジアイス","en":"Regice"},"level":1},{"pid":379,"type":["Steel"],"name":{"zh":"雷吉斯奇魯","ja":"レジスチル","en":"Registeel"},"level":1}],"machine":[],"egg":[{"pid":88,"type":["Poison"],"name":{"zh":"臭泥","ja":"ベトベター","en":"Grimer"}},{"pid":89,"type":["Poison"],"name":{"zh":"臭臭泥","ja":"ベトベトン","en":"Muk"}},{"pid":92,"type":["Ghost","Poison"],"name":{"zh":"鬼斯","ja":"ゴース","en":"Gastly"}},{"pid":93,"type":["Ghost","Poison"],"name":{"zh":"鬼斯通","ja":"ゴースト","en":"Haunter"}},{"pid":94,"type":["Ghost","Poison"],"name":{"zh":"耿鬼","ja":"ゲンガー","en":"Gengar"}},{"pid":95,"type":["Rock","Ground"],"name":{"zh":"大岩蛇","ja":"イワーク","en":"Onix"}},{"pid":208,"type":["Steel","Ground"],"name":{"zh":"大鋼蛇","ja":"ハガネール","en":"Steelix"}},{"pid":299,"type":["Rock"],"name":{"zh":"朝北鼻","ja":"ノズパス","en":"Nosepass"}}],"tutor":[{"pid":89,"type":["Poison"],"name":{"zh":"臭臭泥","ja":"ベトベトン","en":"Muk"}},{"pid":90,"type":["Water"],"name":{"zh":"大舌貝","ja":"シェルダー","en":"Shellder"}},{"pid":91,"type":["Water","Ice"],"name":{"zh":"刺甲貝","ja":"パルシェン","en":"Cloyster"}},{"pid":93,"type":["Ghost","Poison"],"name":{"zh":"鬼斯通","ja":"ゴースト","en":"Haunter"}},{"pid":94,"type":["Ghost","Poison"],"name":{"zh":"耿鬼","ja":"ゲンガー","en":"Gengar"}},{"pid":102,"type":["Grass","Psychic"],"name":{"zh":"蛋蛋","ja":"タマタマ","en":"Exeggcute"}},{"pid":103,"type":["Grass","Psychic"],"name":{"zh":"椰蛋樹","ja":"ナッシー","en":"Exeggutor"}},{"pid":151,"type":["Psychic"],"name":{"zh":"夢幻","ja":"ミュウ","en":"Mew"}},{"pid":185,"type":["Rock"],"name":{"zh":"樹才怪","ja":"ウソッキー","en":"Sudowoodo"}},{"pid":208,"type":["Steel","Ground"],"name":{"zh":"大鋼蛇","ja":"ハガネール","en":"Steelix"}},{"pid":222,"type":["Water","Rock"],"name":{"zh":"太陽珊瑚","ja":"サニーゴ","en":"Corsola"}},{"pid":274,"type":["Grass","Dark"],"name":{"zh":"長鼻葉","ja":"コノハナ","en":"Nuzleaf"}},{"pid":275,"type":["Grass","Dark"],"name":{"zh":"狡猾天狗","ja":"ダーテング","en":"Shiftry"}},{"pid":316,"type":["Poison"],"name":{"zh":"溶食獸","ja":"ゴクリン","en":"Gulpin"}},{"pid":317,"type":["Poison"],"name":{"zh":"吞食獸","ja":"マルノーム","en":"Swalot"}},{"pid":323,"type":["Fire","Ground"],"name":{"zh":"噴火駝","ja":"バクーダ","en":"Camerupt"}},{"pid":324,"type":["Fire"],"name":{"zh":"煤炭龜","ja":"コータス","en":"Torkoal"}},{"pid":362,"type":["Ice"],"name":{"zh":"冰鬼護","ja":"オニゴーリ","en":"Glalie"}},{"pid":375,"type":["Steel","Psychic"],"name":{"zh":"金屬怪","ja":"メタング","en":"Metang"}},{"pid":376,"type":["Steel","Psychic"],"name":{"zh":"巨金怪","ja":"メタグロス","en":"Metagross"}}]}}