{"id":161,"type":"Normal","category":"Physical","power":80,"accuracy":100,"pp":10,"name":{"ja":"トライアタック","en":"Tri Attack","zh":"三重攻擊"},"learnedBy":{"levelUp":[{"pid":51,"type":["Ground"],"name":{"zh":"三地鼠","ja":"ダグトリオ","en":"Dugtrio"},"level":1},{"pid":82,"type":["Electric","Steel"],"name":{"zh":"三合一磁怪","ja":"レアコイル","en":"Magneton"},"level":44},{"pid":84,"type":["Normal","Flying"],"name":{"zh":"嘟嘟","ja":"ドードー","en":"Doduo"},"level":21},{"pid":85,"type":["Normal","Flying"],"name":{"zh":"嘟嘟利","ja":"ドードリオ","en":"Dodrio"},"level":21},{"pid":137,"type":["Normal"],"name":{"zh":"多邊獸","ja":"ポリゴン","en":"Porygon"},"level":36},{"pid":233,"type":["Normal"],"name":{"zh":"多邊獸Ⅱ","ja":"ポリゴン２","en":"Porygon2"},"level":36}],"machine":[],"egg":[{"pid":21,"type":["Normal","Flying"],"name":{"zh":"烈雀","ja":"オニスズメ","en":"Spearow"}},{"pid":22,"type":["Normal","Flying"],"name":{"zh":"大嘴雀","ja":"オニドリル","en":"Fearow"}}],"tutor":[]}}