{"id":196,"type":"Ice","category":"Special","power":55,"accuracy":95,"pp":15,"name":{"ja":"こごえるかぜ","en":"Icy Wind","zh":"冰凍之風"},"learnedBy":{"levelUp":[{"pid":86,"type":["Water"],"name":{"zh":"小海獅","ja":"パウワウ","en":"Seel"},"level":17},{"pid":87,"type":["Water","Ice"],"name":{"zh":"白海獅","ja":"ジュゴン","en":"Dewgong"},"level":1},{"pid":215,"type":["Dark","Ice"],"name":{"zh":"狃拉","ja":"ニューラ","en":"Sneasel"},"level":43},{"pid":361,"type":["Ice"],"name":{"zh":"雪童子","ja":"ユキワラシ","en":"Snorunt"},"level":16},{"pid":362,"type":["Ice"],"name":{"zh":"冰鬼護","ja":"オニゴーリ","en":"Glalie"},"level":16},{"pid":378,"type":["Ice"],"name":{"zh":"雷吉艾斯","ja":"レジアイス","en":"Regice"},"level":9}],"machine":[],"egg":[],"tutor":[]}}