{"id":268,"type":"Electric","category":"Status","power":null,"accuracy":null,"pp":20,"name":{"ja":"じゅうでん","en":"Charge","zh":"充電"},"learnedBy":{"levelUp":[{"pid":100,"type":["Electric"],"name":{"zh":"霹靂電球","ja":"ビリリダマ","en":"Voltorb"},"level":1},{"pid":101,"type":["Electric"],"name":{"zh":"頑皮雷彈","ja":"マルマイン","en":"Electrode"},"level":1},{"pid":145,"type":["Electric","Flying"],"name":{"zh":"閃電鳥","ja":"サンダー","en":"Zapdos"},"level":61},{"pid":170,"type":["Water","Electric"],"name":{"zh":"燈籠魚","ja":"チョンチー","en":"Chinchou"},"level":49},{"pid":171,"type":["Water","Electric"],"name":{"zh":"電燈怪","ja":"ランターン","en":"Lanturn"},"level":61},{"pid":309,"type":["Electric"],"name":{"zh":"落雷獸","ja":"ラクライ","en":"Electrike"},"level":41},{"pid":310,"type":["Electric"],"name":{"zh":"雷電獸","ja":"ライボルト","en":"Manectric"},"level":53},{"pid":311,"type":["Electric"],"name":{"zh":"正電拍拍","ja":"プラスル","en":"Plusle"},"level":31},{"pid":312,"type":["Electric"],"name":{"zh":"負電拍拍","ja":"マイナン","en":"Minun"},"level":31}],"machine":[],"egg":[{"pid":25,"type":["Electric"],"name":{"zh":"皮卡丘","ja":"ピカチュウ","en":"Pikachu"}},{"pid":26,"type":["Electric"],"name":{"zh":"雷丘","ja":"ライチュウ","en":"Raichu"}},{"pid":172,"type":["Electric"],"name":{"zh":"皮丘","ja":"ピチュー","en":"Pichu"}},{"pid":179,"type":["Electric"],"name":{"zh":"咩利羊","ja":"メリープ","en":"Mareep"}},{"pid":180,"type":["Electric"],"name":{"zh":"茸茸羊","ja":"モココ","en":"Flaaffy"}},{"pid":181,"type":["Electric"],"name":{"zh":"電龍","ja":"デンリュウ","en":"Ampharos"}}],"tutor":[]}}